qngng/__init__.py
qngng/cats/d31-f.json
qngng/cats/d31-m.json
qngng/cats/dug-f.json
qngng/cats/dug-m.json
qngng/cats/icip-f.json
qngng/cats/icip-m.json
qngng/cats/lbl-m.json
qngng/cats/sn-f.json
qngng/cats/sn-m.json
qngng/cats/std-names-f.json
qngng/cats/std-names-m.json
qngng/cats/std-surnames.json
qngng/cats/uda-actors-f.json
qngng/cats/uda-actors-m.json
qngng/cats/uda-hosts-f.json
qngng/cats/uda-hosts-m.json
qngng/cats/uda-singers-f.json
qngng/cats/uda-singers-m.json
qngng/qngng.py
qngng-1.5.0.dist-info/entry_points.txt
qngng-1.5.0.dist-info/LICENSE
qngng-1.5.0.dist-info/WHEEL
qngng-1.5.0.dist-info/METADATA
qngng-1.5.0.dist-info/RECORD
