Metadata-Version: 2.1
Name: qngng
Version: 1.5.0
Summary: The Queb name generator: next generation
Home-page: https://github.com/eepp/qngng/
License: MIT
Keywords: generator,quebec,queb,keb
Author: Philippe Proulx
Author-email: eeppeliteloop@gmail.com
Requires-Python: >=3.4,<4.0
Classifier: Environment :: Console
Classifier: Intended Audience :: System Administrators
Classifier: License :: OSI Approved :: MIT License
Classifier: Natural Language :: English
Classifier: Programming Language :: Python
Classifier: Programming Language :: Python :: 3
Classifier: Programming Language :: Python :: 3 :: Only
Classifier: Programming Language :: Python :: 3.4
Classifier: Programming Language :: Python :: 3.5
Classifier: Programming Language :: Python :: 3.6
Classifier: Programming Language :: Python :: 3.7
Classifier: Programming Language :: Python :: 3.8
Project-URL: Bug tracker, https://github.com/eepp/qngng/issues/
Project-URL: Repository, https://github.com/eepp/qngng/
